envoxyd-0.4.18.data/data/bin/envoxy-cli
envoxyd-0.4.18.data/data/bin/envoxyd
envoxyd-0.4.18.data/purelib/envoxyd/__init__.py
envoxyd-0.4.18.data/purelib/envoxyd/run.py
envoxyd-0.4.18.data/purelib/envoxyd/templates/__init__.py
envoxyd-0.4.18.data/purelib/envoxyd/templates/run.py
envoxyd-0.4.18.data/purelib/envoxyd/templates/view.py
envoxyd-0.4.18.data/purelib/envoxyd/templates/confs/__init__.py
envoxyd-0.4.18.data/purelib/envoxyd/templates/confs/envoxy.json
envoxyd-0.4.18.data/purelib/envoxyd/tools/envoxy-cli
envoxyd.libs/libcrypto-8f00f18b.so.56.0.0
envoxyd.libs/libexpat-e4f7ec7e.so.1.11.1
envoxyd.libs/libpcre2-8-4e09f26e.so.0.12.0
envoxyd.libs/libssl-f8719639.so.59.0.1
envoxyd.libs/libuuid-f3770415.so.1.3.0
envoxyd-0.4.18.dist-info/METADATA
envoxyd-0.4.18.dist-info/WHEEL
envoxyd-0.4.18.dist-info/top_level.txt
envoxyd-0.4.18.dist-info/RECORD
