Metadata-Version: 2.4
Name: envoxyd
Version: 0.4.18
Summary: Customized uWSGI server for Envoxy
Home-page: https://github.com/habitio/envoxy
Author: Matheus (vorjdux) Santos
Author-email: "Matheus (vorjdux) Santos" <vorj.dux@gmail.com>, Laoska Guadamuz <laoska@benyasca.com>
Project-URL: Homepage, https://github.com/habitio/envoxy
Classifier: License :: OSI Approved :: MIT License
Classifier: Programming Language :: Python :: 3
Classifier: Programming Language :: Python :: 3.12
Classifier: Operating System :: POSIX :: Linux
Classifier: Development Status :: 4 - Beta
Requires-Python: >=3.12
Requires-Dist: envoxy>=0.5.18
Requires-Dist: flask-cors==6.0.1
Requires-Dist: isort==7.0.0
Dynamic: author
Dynamic: home-page
Dynamic: requires-python
